filelock/__init__.py
filelock/_api.py
filelock/_error.py
filelock/_soft.py
filelock/_unix.py
filelock/_util.py
filelock/_windows.py
filelock/asyncio.py
filelock/py.typed
filelock_lts_py39-2025.68146.2.dist-info/licenses/LICENSE
filelock_lts_py39-2025.68146.2.dist-info/METADATA
filelock_lts_py39-2025.68146.2.dist-info/WHEEL
filelock_lts_py39-2025.68146.2.dist-info/top_level.txt
filelock_lts_py39-2025.68146.2.dist-info/RECORD
