Metadata-Version: 2.4
Name: filelock-lts-py39
Version: 2025.68146.2
Summary: Python 3.9 compatible filelock with CVE-2025-68146 patch
License: Unlicense
Project-URL: Homepage, https://github.com/1minds3t/filelock-lts
Classifier: Programming Language :: Python :: 3.9
Requires-Python: <3.10,>=3.9
License-File: LICENSE
Dynamic: license-file
